fastapi_motor_oil/__init__.py
fastapi_motor_oil/bound_method_wrapper.py
fastapi_motor_oil/delete_rule.py
fastapi_motor_oil/model.py
fastapi_motor_oil/py.typed
fastapi_motor_oil/service.py
fastapi_motor_oil/typing.py
fastapi_motor_oil/validator.py
fastapi_motor_oil-0.5.2.dist-info/LICENSE
fastapi_motor_oil-0.5.2.dist-info/METADATA
fastapi_motor_oil-0.5.2.dist-info/WHEEL
fastapi_motor_oil-0.5.2.dist-info/RECORD
