Metadata-Version: 2.1
Name: fastapi-motor-oil
Version: 0.5.2
Summary: Collection of async utilities for working with MongoDB and conveniently creating performant APIs with async web frameworks such a FastAPI.
Author: Peter Volf
Author-email: do.volfp@gmail.com
Requires-Python: >=3.10,<4.0
Classifier: Programming Language :: Python :: 3
Classifier: Programming Language :: Python :: 3.10
Classifier: Programming Language :: Python :: 3.11
Requires-Dist: motor (>=3.1.1,<4.0.0)
Requires-Dist: pydantic (>=1.10.5,<2.0.0)
